Workbook

Sheet INPUTS
A1: Parameter | B1: Value | C1: Unit | D1: Log ID | E1: Rating | G1: Rule: no hardcoded numbers outside this tab.
A2: Baseline annual claims cost (real $) | B2: 2500000 | C2: $/yr | D2: L1 | E2: SOURCED
A3: Average payment per claim | B3: 53000 | C3: $/claim | D3: L2 | E3: SOURCED
A4: Annual CIP replacement need | B4: 16100000 | C4: $/yr | D4: V1 | E4: SOURCED
A5: Actual avg CIP investment (FY18-24) | B5: 1570000 | C5: $/yr | D5: V2 | E5: SOURCED
A6: City share of repair responsibility | B6: 0.5 | C6: share | D6: B3 | E6: SOURCED (TD estimate)
A7: Hazard population (2014-15 assessment) | B7: 85000 | C7: locations | D7: B1 | E7: SOURCED
A8: City-responsibility replacement backlog | B8: 8500 | C8: locations | D8: B2 | E8: SOURCED (midpoint 8-9K)
A9: Ramping capacity unit cost (4 rampers FY24) | B9: 900000 | C9: $ | D9: B5 | E9: SOURCED
A10: Mitigation effectiveness (claims avoided at full rollout) | B10: 0.3 | C10: share | D10: E1 | E10: ESTIMATE - PLACEHOLDER
A11: Cost per location mitigated (ramp/slice) | B11: 300 | C11: $/location | D11: E1b | E11: ESTIMATE - PLACEHOLDER
A12: Option B target rollout (share of hazards mitigated) | B12: 0.6 | C12: share | D12: MB1 | E12: ESTIMATE - policy lever
A13: Option C funding level (share of V1 need) | B13: 1 | C13: share | D13: MC1 | E13: ESTIMATE - policy lever
... A17: Total sidewalk capital need (FY25-29 outlook) | B17: 104000000 | C17: $ | D17: V3 | E17: SOURCED

Sheet NPV
A1: Year | B1: DiscFactor | C1: Claims_A | D1: Outlay_B | E1: Claims_B | F1: Net_B_vs_A | G1: PV_B | H1: Outlay_C | I1: CumClearShare_C | J1: Claims_C | K1: Net_C_vs_A | L1: PV_C | N1: NPV Option B vs A: | O1: =SUM($G$2:$G$21)
A2: 1 | B2: =IF($A2<=INPUTS!$B$16,1/(1+INPUTS!$B$15)^$A2,0) | C2: =IF($B2=0,0,INPUTS!$B$2) | D2: =IF(AND($B2>0,$A2<=3),INPUTS!$B$12*INPUTS!$B$7*INPUTS!$B$11/3,0) | E2: =IF($B2=0,0,INPUTS!$B$2*(1-MIN($A2/3,1)*INPUTS!$B$12*INPUTS!$B$10)) | F2: =($C2-$E2)-$D2 | G2: =$F2*$B2 | H2: =IF($B2=0,0,MAX(0,INPUTS!$B$13*INPUTS!$B$4-INPUTS!$B$5)) | I2: =MIN(1,SUM($H$2:$H2)/INPUTS!$B$17) | J2: =IF($B2=0,0,INPUTS!$B$2*(1-$I2*INPUTS!$B$14)) | K2: =($C2-$J2)-$H2 | L2: =$K2*$B2 | N2: NPV Option C vs A: | O2: =SUM($L$2:$L$21)
A3: 2 | B3: =IF($A3<=INPUTS!$B$16,1/(1+INPUTS!$B$15)^$A3,0) | C3: =IF($B3=0,0,INPUTS!$B$2) | D3: =IF(AND($B3>0,$A3<=3),INPUTS!$B$12*INPUTS!$B$7*INPUTS!$B$11/3,0) | E3: =IF($B3=0,0,INPUTS!$B$2*(1-MIN($A3/3,1)*INPUTS!$B$12*INPUTS!$B$10)) | F3: =($C3-$E3)-$D3 | G3: =$F3*$B3 | H3: =IF($B3=0,0,MAX(0,INPUTS!$B$13*INPUTS!$B$4-INPUTS!$B$5)) | I3: =MIN(1,SUM($H$2:$H3)/INPUTS!$B$17) | J3: =IF($B3=0,0,INPUTS!$B$2*(1-$I3*INPUTS!$B$14)) | K3: =($C3-$J3)-$H3 | L3: =$K3*$B3
A4: 3 | B4: =IF($A4<=INPUTS!$B$16,1/(1+INPUTS!$B$15)^$A4,0) | C4: =IF($B4=0,0,INPUTS!$B$2) | D4: =IF(AND($B4>0,$A4<=3),INPUTS!$B$12*INPUTS!$B$7*INPUTS!$B$11/3,0) | E4: =IF($B4=0,0,INPUTS!$B$2*(1-MIN($A4/3,1)*INPUTS!$B$12*INPUTS!$B$10)) | F4: =($C4-$E4)-$D4 | G4: =$F4*$B4 | H4: =IF($B4=0,0,MAX(0,INPUTS!$B$13*INPUTS!$B$4-INPUTS!$B$5)) | I4: =MIN(1,SUM($H$2:$H4)/INPUTS!$B$17) | J4: =IF($B4=0,0,INPUTS!$B$2*(1-$I4*INPUTS!$B$14)) | K4: =($C4-$J4)-$H4 | L4: =$K4*$B4 | N4: Option B rollout spends over years 1-3; claims effect phases in with completion. Upkeep/re-mitigation not yet modeled - log it.
A5: 4 | B5: =IF($A5<=INPUTS!$B$16,1/(1+INPUTS!$B$15)^$A5,0) | C5: =IF($B5=0,0,INPUTS!$B$2) | D5: =IF(AND($B5>0,$A5<=3),INPUTS!$B$12*INPUTS!$B$7*INPUTS!$B$11/3,0) | E5: =IF($B5=0,0,INPUTS!$B$2*(1-MIN($A5/3,1)*INPUTS!$B$12*INPUTS!$B$10)) | F5: =($C5-$E5)-$D5 | G5: =$F5*$B5 | H5: =IF($B5=0,0,MAX(0,INPUTS!$B$13*INPUTS!$B$4-INPUTS!$B$5)) | I5: =MIN(1,SUM($H$2:$H5)/INPUTS!$B$17) | J5: =IF($B5=0,0,INPUTS!$B$2*(1-$I5*INPUTS!$B$14)) | K5: =($C5-$J5)-$H5 | L5: =$K5*$B5
A6: 5 | B6: =IF($A6<=INPUTS!$B$16,1/(1+INPUTS!$B$15)^$A6,0) | C6: =IF($B6=0,0,INPUTS!$B$2) | D6: =IF(AND($B6>0,$A6<=3),INPUTS!$B$12*INPUTS!$B$7*INPUTS!$B$11/3,0) | E6: =IF($B6=0,0,INPUTS!$B$2*(1-MIN($A6/3,1)*INPUTS!$B$12*INPUTS!$B$10)) | F6: =($C6-$E6)-$D6 | G6: =$F6*$B6 | H6: =IF($B6=0,0,MAX(0,INPUTS!$B$13*INPUTS!$B$4-INPUTS!$B$5)) | I6: =MIN(1,SUM($H$2:$H6)/INPUTS!$B$17) | J6: =IF($B6=0,0,INPUTS!$B$2*(1-$I6*INPUTS!$B$14)) | K6: =($C6-$J6)-$H6 | L6: =$K6*$B6
A7: 6 | B7: =IF($A7<=INPUTS!$B$16,1/(1+INPUTS!$B$15)^$A7,0) | C7: =IF($B7=0,0,INPUTS!$B$2) | D7: =IF(AND($B7>0,$A7<=3),INPUTS!$B$12*INPUTS!$B$7*INPUTS!$B$11/3,0) | E7: =IF($B7=0,0,INPUTS!$B$2*(1-MIN($A7/3,1)*INPUTS!$B$12*INPUTS!$B$10)) | F7: =($C7-$E7)-$D7 | G7: =$F7*$B7 | H7: =IF($B7=0,0,MAX(0,INPUTS!$B$13*INPUTS!$B$4-INPUTS!$B$5)) | I7: =MIN(1,SUM($H$2:$H7)/INPUTS!$B$17) | J7: =IF($B7=0,0,INPUTS!$B$2*(1-$I7*INPUTS!$B$14)) | K7: =($C7-$J7)-$H7 | L7: =$K7*$B7
A8: 7 | B8: =IF($A8<=INPUTS!$B$16,1/(1+INPUTS!$B$15)^$A8,0) | C8: =IF($B8=0,0,INPUTS!$B$2) | D8: =IF(AND($B8>0,$A8<=3),INPUTS!$B$12*INPUTS!$B$7*INPUTS!$B$11/3,0) | E8: =IF($B8=0,0,INPUTS!$B$2*(1-MIN($A8/3,1)*INPUTS!$B$12*INPUTS!$B$10)) | F8: =($C8-$E8)-$D8 | G8: =$F8*$B8 | H8: =IF($B8=0,0,MAX(0,INPUTS!$B$13*INPUTS!$B$4-INPUTS!$B$5)) | I8: =MIN(1,SUM($H$2:$H8)/INPUTS!$B$17) | J8: =IF($B8=0,0,INPUTS!$B$2*(1-$I8*INPUTS!$B$14)) | K8: =($C8-$J8)-$H8 | L8: =$K8*$B8
A9: 8 | B9: =IF($A9<=INPUTS!$B$16,1/(1+INPUTS!$B$15)^$A9,0) | C9: =IF($B9=0,0,INPUTS!$B$2) | D9: =IF(AND($B9>0,$A9<=3),INPUTS!$B$12*INPUTS!$B$7*INPUTS!$B$11/3,0) | E9: =IF($B9=0,0,INPUTS!$B$2*(1-MIN($A9/3,1)*INPUTS!$B$12*INPUTS!$B$10)) | F9: =($C9-$E9)-$D9 | G9: =$F9*$B9 | H9: =IF($B9=0,0,MAX(0,INPUTS!$B$13*INPUTS!$B$4-INPUTS!$B$5)) | I9: =MIN(1,SUM($H$2:$H9)/INPUTS!$B$17) | J9: =IF($B9=0,0,INPUTS!$B$2*(1-$I9*INPUTS!$B$14)) | K9: =($C9-$J9)-$H9 | L9: =$K9*$B9
A10: 9 | B10: =IF($A10<=INPUTS!$B$16,1/(1+INPUTS!$B$15)^$A10,0) | C10: =IF($B10=0,0,INPUTS!$B$2) | D10: =IF(AND($B10>0,$A10<=3),INPUTS!$B$12*INPUTS!$B$7*INPUTS!$B$11/3,0) | E10: =IF($B10=0,0,INPUTS!$B$2*(1-MIN($A10/3,1)*INPUTS!$B$12*INPUTS!$B$10)) | F10: =($C10-$E10)-$D10 | G10: =$F10*$B10 | H10: =IF($B10=0,0,MAX(0,INPUTS!$B$13*INPUTS!$B$4-INPUTS!$B$5)) | I10: =MIN(1,SUM($H$2:$H10)/INPUTS!$B$17) | J10: =IF($B10=0,0,INPUTS!$B$2*(1-$I10*INPUTS!$B$14)) | K10: =($C10-$J10)-$H10 | L10: =$K10*$B10
A11: 10 | B11: =IF($A11<=INPUTS!$B$16,1/(1+INPUTS!$B$15)^$A11,0) | C11: =IF($B11=0,0,INPUTS!$B$2) | D11: =IF(AND($B11>0,$A11<=3),INPUTS!$B$12*INPUTS!$B$7*INPUTS!$B$11/3,0) | E11: =IF($B11=0,0,INPUTS!$B$2*(1-MIN($A11/3,1)*INPUTS!$B$12*INPUTS!$B$10)) | F11: =($C11-$E11)-$D11 | G11: =$F11*$B11 | H11: =IF($B11=0,0,MAX(0,INPUTS!$B$13*INPUTS!$B$4-INPUTS!$B$5)) | I11: =MIN(1,SUM($H$2:$H11)/INPUTS!$B$17) | J11: =IF($B11=0,0,INPUTS!$B$2*(1-$I11*INPUTS!$B$14)) | K11: =($C11-$J11)-$H11 | L11: =$K11*$B11
A12: 11 | B12: =IF($A12<=INPUTS!$B$16,1/(1+INPUTS!$B$15)^$A12,0) | C12: =IF($B12=0,0,INPUTS!$B$2) | D12: =IF(AND($B12>0,$A12<=3),INPUTS!$B$12*INPUTS!$B$7*INPUTS!$B$11/3,0) | E12: =IF($B12=0,0,INPUTS!$B$2*(1-MIN($A12/3,1)*INPUTS!$B$12*INPUTS!$B$10)) | F12: =($C12-$E12)-$D12 | G12: =$F12*$B12 | H12: =IF($B12=0,0,MAX(0,INPUTS!$B$13*INPUTS!$B$4-INPUTS!$B$5)) | I12: =MIN(1,SUM($H$2:$H12)/INPUTS!$B$17) | J12: =IF($B12=0,0,INPUTS!$B$2*(1-$I12*INPUTS!$B$14)) | K12: =($C12-$J12)-$H12 | L12: =$K12*$B12
A13: 12 | B13: =IF($A13<=INPUTS!$B$16,1/(1+INPUTS!$B$15)^$A13,0) | C13: =IF($B13=0,0,INPUTS!$B$2) | D13: =IF(AND($B13>0,$A13<=3),INPUTS!$B$12*INPUTS!$B$7*INPUTS!$B$11/3,0) | E13: =IF($B13=0,0,INPUTS!$B$2*(1-MIN($A13/3,1)*INPUTS!$B$12*INPUTS!$B$10)) | F13: =($C13-$E13)-$D13 | G13: =$F13*$B13 | H13: =IF($B13=0,0,MAX(0,INPUTS!$B$13*INPUTS!$B$4-INPUTS!$B$5)) | I13: =MIN(1,SUM($H$2:$H13)/INPUTS!$B$17) | J13: =IF($B13=0,0,INPUTS!$B$2*(1-$I13*INPUTS!$B$14)) | K13: =($C13-$J13)-$H13 | L13: =$K13*$B13
A14: 13 | B14: =IF($A14<=INPUTS!$B$16,1/(1+INPUTS!$B$15)^$A14,0) | C14: =IF($B14=0,0,INPUTS!$B$2) | D14: =IF(AND($B14>0,$A14<=3),INPUTS!$B$12*INPUTS!$B$7*INPUTS!$B$11/3,0) | E14: =IF($B14=0,0,INPUTS!$B$2*(1-MIN($A14/3,1)*INPUTS!$B$12*INPUTS!$B$10)) | F14: =($C14-$E14)-$D14 | G14: =$F14*$B14 | H14: =IF($B14=0,0,MAX(0,INPUTS!$B$13*INPUTS!$B$4-INPUTS!$B$5)) | I14: =MIN(1,SUM($H$2:$H14)/INPUTS!$B$17) | J14: =IF($B14=0,0,INPUTS!$B$2*(1-$I14*INPUTS!$B$14)) | K14: =($C14-$J14)-$H14 | L14: =$K14*$B14
A15: 14 | B15: =IF($A15<=INPUTS!$B$16,1/(1+INPUTS!$B$15)^$A15,0) | C15: =IF($B15=0,0,INPUTS!$B$2) | D15: =IF(AND($B15>0,$A15<=3),INPUTS!$B$12*INPUTS!$B$7*INPUTS!$B$11/3,0) | E15: =IF($B15=0,0,INPUTS!$B$2*(1-MIN($A15/3,1)*INPUTS!$B$12*INPUTS!$B$10)) | F15: =($C15-$E15)-$D15 | G15: =$F15*$B15 | H15: =IF($B15=0,0,MAX(0,INPUTS!$B$13*INPUTS!$B$4-INPUTS!$B$5)) | I15: =MIN(1,SUM($H$2:$H15)/INPUTS!$B$17) | J15: =IF($B15=0,0,INPUTS!$B$2*(1-$I15*INPUTS!$B$14)) | K15: =($C15-$J15)-$H15 | L15: =$K15*$B15
A16: 15 | B16: =IF($A16<=INPUTS!$B$16,1/(1+INPUTS!$B$15)^$A16,0) | C16: =IF($B16=0,0,INPUTS!$B$2) | D16: =IF(AND($B16>0,$A16<=3),INPUTS!$B$12*INPUTS!$B$7*INPUTS!$B$11/3,0) | E16: =IF($B16=0,0,INPUTS!$B$2*(1-MIN($A16/3,1)*INPUTS!$B$12*INPUTS!$B$10)) | F16: =($C16-$E16)-$D16 | G16: =$F16*$B16 | H16: =IF($B16=0,0,MAX(0,INPUTS!$B$13*INPUTS!$B$4-INPUTS!$B$5)) | I16: =MIN(1,SUM($H$2:$H16)/INPUTS!$B$17) | J16: =IF($B16=0,0,INPUTS!$B$2*(1-$I16*INPUTS!$B$14)) | K16: =($C16-$J16)-$H16 | L16: =$K16*$B16
... A21: 20 | B21: =IF($A21<=INPUTS!$B$16,1/(1+INPUTS!$B$15)^$A21,0) | C21: =IF($B21=0,0,INPUTS!$B$2) | D21: =IF(AND($B21>0,$A21<=3),INPUTS!$B$12*INPUTS!$B$7*INPUTS!$B$11/3,0) | E21: =IF($B21=0,0,INPUTS!$B$2*(1-MIN($A21/3,1)*INPUTS!$B$12*INPUTS!$B$10)) | F21: =($C21-$E21)-$D21 | G21: =$F21*$B21 | H21: =IF($B21=0,0,MAX(0,INPUTS!$B$13*INPUTS!$B$4-INPUTS!$B$5)) | I21: =MIN(1,SUM($H$2:$H21)/INPUTS!$B$17) | J21: =IF($B21=0,0,INPUTS!$B$2*(1-$I21*INPUTS!$B$14)) | K21: =($C21-$J21)-$H21 | L21: =$K21*$B21

Sheet OUTPUT
A1: Headline | B1: Value
A2: NPV Option B vs do-nothing (Python base = NPV tab) | B2: -11019978
A3: NPV, replacement acceleration (C) vs do nothing | B3: =NPV!$O$2
A4: E1 effectiveness assumption driving B | B4: =INPUTS!$B$10
A5: Memo rule: cite ONLY cells on this tab.

Sheet CLAIMS
A1: Hand-build per spec: 2015-21 series detail, severity distribution incl. L4 tail.

Sheet OPTIONS
A1: Hand-build per spec: per-option cost detail; NPV tab holds v0 math.

Sheet SENSITIVITY
A1: TORNADO (Python-computed; ranges trace to assumptions-log IDs; E1 floored at 0.0 per LA natural experiment)
A3: Input | B3: Low NPV_B | C3: High NPV_B | D3: Swing | E3: Base NPV_B | F3: Range rationale
A4: Cost per location mitigated | B4: -3807019 | C4: -25445896 | D4: 21638877 | E4: -11019978 | F4: E1b ESTIMATE anchored to B5 ramping-crew cost; log rule: every ESTIMATE stays in the tornado
A5: Option B rollout share | B5: -5509989 | C5: -16529967 | D5: 11019978 | E5: -11019978 | F5: policy lever, not uncertainty - shown for completeness; scenario axis in the memo
A6: E1 mitigation effectiveness | B6: -14425918 | C6: -8749352 | D6: 5676566 | E6: -11019978 | F6: floor 0.0 = LA untargeted downside (E1 evidence base); 0.50 targeted upper remains a guess
A7: Horizon (years) | B7: -12797701 | C7: -8163706 | D7: 4633995 | E7: -11019978 | F7: F2; vs B9 50-75yr useful life
A8: Baseline annual claims | B8: -11701166 | C8: -10475028 | D8: 1226138 | E8: -11019978 | F8: L1 2015-21 avg to L3 FY23 high
A9: Discount rate | B9: -11103934 | C9: -10634790 | D9: 469145 | E9: -11019978 | F9: F1 regime flux: A-94 Appendix C ~2% to reinstated 7% base
A12: TWO-WAY: NPV_B by E1 (rows) x $/location (cols). Rebuild as a live Excel Data Table in the hand-finished workbook (What-If Analysis; corner ='NPV'!O1, row input INPUTS!B11, col input INPUTS!B10).
A13: E1 \ $loc | B13: 150 | C13: 250 | D13: 350 | E13: 450 | F13: 600
A14: 0 | B14: -7212959 | C14: -12021598 | D14: -16830238 | E14: -21638877 | F14: -28851836
A15: 0.1 | B15: -6077646 | C15: -10886285 | D15: -15694924 | E15: -20503564 | F15: -27716523
A16: 0.2 | B16: -4942332 | C16: -9750972 | D16: -14559611 | E16: -19368250 | F16: -26581209
A17: 0.3 | B17: -3807019 | C17: -8615659 | D17: -13424298 | E17: -18232937 | F17: -25445896
A18: 0.4 | B18: -2671706 | C18: -7480345 | D18: -12288985 | E18: -17097624 | F18: -24310583
A19: 0.5 | B19: -1536393 | C19: -6345032 | D19: -11153671 | E19: -15962311 | F19: -23175270
